azure_pyproxy
