Metadata-Version: 2.1
Name: AzurePyProxy
Version: 1.1b0
Summary: This package provides proxy class for calling azure commands directly from Python.
Home-page: https://github.com/tomasvotava/azure-pyproxy
Author: Tomas Votava
Author-email: info@tomasvotava.eu
License: MIT License
Download-URL: https://github.com/tomasvotava/azure-pyproxy/archive/master.zip
Project-URL: Bug Tracker, https://github.com/tomasvotava/azure-pyproxy/issues
Project-URL: Documentation, https://github.com/tomasvotava/azure-pyproxy/blob/master/README.md
Project-URL: Source Code, https://github.com/tomasvotava/azure-pyproxy
Keywords: azure platform azure python proxy
Platform: UNKNOWN
Classifier: License :: OSI Approved :: MIT License
Classifier: Programming Language :: Python :: 3
Classifier: Topic :: Software Development :: Build Tools
Classifier: Development Status :: 4 - Beta
